{
  "boxScoreLink": "/boxscores/201509270crd.htm",
  "playerStatsList": [
    {
      "playerLink": "/players/K/KaepCo00.htm",
      "playerName": "Colin Kaepernick",
      "team": "SFO",
      "passing": {
        "cmp": "9",
        "att": "19",
        "yds": "67",
        "td": "0",
        "int": "4",
        "sk": "2",
        "lng": "14",
        "rate": "16.7"
      },
      "rushing": {
        "att": "7",
        "yds": "46",
        "td": "1",
        "lng": "12"
      },
      "receiving": {
        "tgt": "0",
        "rec": "0",
        "yds": "0",
        "td": "0",
        "lng": "0"
      },
      "fumbles": {
        "fmb": "0",
        "fl": "0"
      }
    },
    {
      "playerLink": "/players/H/HydeCa00.htm",
      "playerName": "Carlos Hyde",
      "team": "SFO",
      "passing": {
        "cmp": "0",
        "att": "0",
        "yds": "0",
        "td": "0",
        "int": "0",
        "sk": "0",
        "lng": "0",
        "rate": ""
      },
      "rushing": {
        "att": "15",
        "yds": "51",
        "td": "0",
        "lng": "14"
      },
      "receiving": {
        "tgt": "1",
        "rec": "1",
        "yds": "10",
        "td": "0",
        "lng": "10"
      },
      "fumbles": {
        "fmb": "0",
        "fl": "0"
      }
    },
    {
      "playerLink": "/players/D/DaviMi01.htm",
      "playerName": "Mike Davis",
      "team": "SFO",
      "passing": {
        "cmp": "0",
        "att": "0",
        "yds": "0",
        "td": "0",
        "int": "0",
        "sk": "0",
        "lng": "0",
        "rate": ""
      },
      "rushing": {
        "att": "7",
        "yds": "6",
        "td": "0",
        "lng": "4"
      },
      "receiving": {
        "tgt": "3",
        "rec": "1",
        "yds": "5",
        "td": "0",
        "lng": "5"
      },
      "fumbles": {
        "fmb": "0",
        "fl": "0"
      }
    },
    {
      "playerLink": "/players/C/CeleGa00.htm",
      "playerName": "Garrett Celek",
      "team": "SFO",
      "passing": {
        "cmp": "0",
        "att": "0",
        "yds": "0",
        "td": "0",
        "int": "0",
        "sk": "0",
        "lng": "0",
        "rate": ""
      },
      "rushing": {
        "att": "0",
        "yds": "0",
        "td": "0",
        "lng": "0"
      },
      "receiving": {
        "tgt": "3",
        "rec": "3",
        "yds": "29",
        "td": "0",
        "lng": "12"
      },
      "fumbles": {
        "fmb": "0",
        "fl": "0"
      }
    },
    {
      "playerLink": "/players/B/BoldAn00.htm",
      "playerName": "Anquan Boldin",
      "team": "SFO",
      "passing": {
        "cmp": "0",
        "att": "0",
        "yds": "0",
        "td": "0",
        "int": "0",
        "sk": "0",
        "lng": "0",
        "rate": ""
      },
      "rushing": {
        "att": "0",
        "yds": "0",
        "td": "0",
        "lng": "0"
      },
      "receiving": {
        "tgt": "4",
        "rec": "2",
        "yds": "16",
        "td": "0",
        "lng": "14"
      },
      "fumbles": {
        "fmb": "0",
        "fl": "0"
      }
    },
    {
      "playerLink": "/players/P/PattQu00.htm",
      "playerName": "Quinton Patton",
      "team": "SFO",
      "passing": {
        "cmp": "0",
        "att": "0",
        "yds": "0",
        "td": "0",
        "int": "0",
        "sk": "0",
        "lng": "0",
        "rate": ""
      },
      "rushing": {
        "att": "0",
        "yds": "0",
        "td": "0",
        "lng": "0"
      },
      "receiving": {
        "tgt": "3",
        "rec": "1",
        "yds": "7",
        "td": "0",
        "lng": "7"
      },
      "fumbles": {
        "fmb": "0",
        "fl": "0"
      }
    },
    {
      "playerLink": "/players/B/BellBl00.htm",
      "playerName": "Blake Bell",
      "team": "SFO",
      "passing": {
        "cmp": "0",
        "att": "0",
        "yds": "0",
        "td": "0",
        "int": "0",
        "sk": "0",
        "lng": "0",
        "rate": ""
      },
      "rushing": {
        "att": "0",
        "yds": "0",
        "td": "0",
        "lng": "0"
      },
      "receiving": {
        "tgt": "1",
        "rec": "1",
        "yds": "0",
        "td": "0",
        "lng": "0"
      },
      "fumbles": {
        "fmb": "0",
        "fl": "0"
      }
    },
    {
      "playerLink": "/players/P/PalmCa00.htm",
      "playerName": "Carson Palmer",
      "team": "ARI",
      "passing": {
        "cmp": "20",
        "att": "32",
        "yds": "311",
        "td": "2",
        "int": "1",
        "sk": "1",
        "lng": "40",
        "rate": "102.5"
      },
      "rushing": {
        "att": "1",
        "yds": "1",
        "td": "0",
        "lng": "1"
      },
      "receiving": {
        "tgt": "0",
        "rec": "0",
        "yds": "0",
        "td": "0",
        "lng": "0"
      },
      "fumbles": {
        "fmb": "1",
        "fl": "0"
      }
    },
    {
      "playerLink": "/players/J/JohnCh04.htm",
      "playerName": "Chris Johnson",
      "team": "ARI",
      "passing": {
        "cmp": "0",
        "att": "0",
        "yds": "0",
        "td": "0",
        "int": "0",
        "sk": "0",
        "lng": "0",
        "rate": ""
      },
      "rushing": {
        "att": "22",
        "yds": "110",
        "td": "2",
        "lng": "30"
      },
      "receiving": {
        "tgt": "2",
        "rec": "1",
        "yds": "40",
        "td": "0",
        "lng": "40"
      },
      "fumbles": {
        "fmb": "0",
        "fl": "0"
      }
    },
    {
      "playerLink": "/players/J/JohnDa08.htm",
      "playerName": "David Johnson",
      "team": "ARI",
      "passing": {
        "cmp": "0",
        "att": "0",
        "yds": "0",
        "td": "0",
        "int": "0",
        "sk": "0",
        "lng": "0",
        "rate": ""
      },
      "rushing": {
        "att": "7",
        "yds": "25",
        "td": "0",
        "lng": "8"
      },
      "receiving": {
        "tgt": "3",
        "rec": "3",
        "yds": "16",
        "td": "0",
        "lng": "9"
      },
      "fumbles": {
        "fmb": "0",
        "fl": "0"
      }
    },
    {
      "playerLink": "/players/T/TaylSt00.htm",
      "playerName": "Stepfan Taylor",
      "team": "ARI",
      "passing": {
        "cmp": "0",
        "att": "0",
        "yds": "0",
        "td": "0",
        "int": "0",
        "sk": "0",
        "lng": "0",
        "rate": ""
      },
      "rushing": {
        "att": "4",
        "yds": "6",
        "td": "0",
        "lng": "2"
      },
      "receiving": {
        "tgt": "0",
        "rec": "0",
        "yds": "0",
        "td": "0",
        "lng": "0"
      },
      "fumbles": {
        "fmb": "0",
        "fl": "0"
      }
    },
    {
      "playerLink": "/players/F/FitzLa00.htm",
      "playerName": "Larry Fitzgerald",
      "team": "ARI",
      "passing": {
        "cmp": "0",
        "att": "0",
        "yds": "0",
        "td": "0",
        "int": "0",
        "sk": "0",
        "lng": "0",
        "rate": ""
      },
      "rushing": {
        "att": "0",
        "yds": "0",
        "td": "0",
        "lng": "0"
      },
      "receiving": {
        "tgt": "11",
        "rec": "9",
        "yds": "134",
        "td": "2",
        "lng": "23"
      },
      "fumbles": {
        "fmb": "0",
        "fl": "0"
      }
    },
    {
      "playerLink": "/players/B/BrowJo02.htm",
      "playerName": "John Brown",
      "team": "ARI",
      "passing": {
        "cmp": "0",
        "att": "0",
        "yds": "0",
        "td": "0",
        "int": "0",
        "sk": "0",
        "lng": "0",
        "rate": ""
      },
      "rushing": {
        "att": "0",
        "yds": "0",
        "td": "0",
        "lng": "0"
      },
      "receiving": {
        "tgt": "5",
        "rec": "3",
        "yds": "62",
        "td": "0",
        "lng": "27"
      },
      "fumbles": {
        "fmb": "0",
        "fl": "0"
      }
    },
    {
      "playerLink": "/players/G/GresJe00.htm",
      "playerName": "Jermaine Gresham",
      "team": "ARI",
      "passing": {
        "cmp": "0",
        "att": "0",
        "yds": "0",
        "td": "0",
        "int": "0",
        "sk": "0",
        "lng": "0",
        "rate": ""
      },
      "rushing": {
        "att": "0",
        "yds": "0",
        "td": "0",
        "lng": "0"
      },
      "receiving": {
        "tgt": "3",
        "rec": "2",
        "yds": "34",
        "td": "0",
        "lng": "22"
      },
      "fumbles": {
        "fmb": "0",
        "fl": "0"
      }
    },
    {
      "playerLink": "/players/F/FellDa01.htm",
      "playerName": "Darren Fells",
      "team": "ARI",
      "passing": {
        "cmp": "0",
        "att": "0",
        "yds": "0",
        "td": "0",
        "int": "0",
        "sk": "0",
        "lng": "0",
        "rate": ""
      },
      "rushing": {
        "att": "0",
        "yds": "0",
        "td": "0",
        "lng": "0"
      },
      "receiving": {
        "tgt": "2",
        "rec": "1",
        "yds": "13",
        "td": "0",
        "lng": "13"
      },
      "fumbles": {
        "fmb": "0",
        "fl": "0"
      }
    },
    {
      "playerLink": "/players/F/FloyMi00.htm",
      "playerName": "Michael Floyd",
      "team": "ARI",
      "passing": {
        "cmp": "0",
        "att": "0",
        "yds": "0",
        "td": "0",
        "int": "0",
        "sk": "0",
        "lng": "0",
        "rate": ""
      },
      "rushing": {
        "att": "0",
        "yds": "0",
        "td": "0",
        "lng": "0"
      },
      "receiving": {
        "tgt": "5",
        "rec": "1",
        "yds": "12",
        "td": "0",
        "lng": "12"
      },
      "fumbles": {
        "fmb": "0",
        "fl": "0"
      }
    },
    {
      "playerLink": "/players/S/StanDr00.htm",
      "playerName": "Drew Stanton",
      "team": "ARI",
      "passing": {
        "cmp": "0",
        "att": "0",
        "yds": "0",
        "td": "0",
        "int": "0",
        "sk": "0",
        "lng": "0",
        "rate": ""
      },
      "rushing": {
        "att": "3",
        "yds": "-3",
        "td": "0",
        "lng": "-1"
      },
      "receiving": {
        "tgt": "0",
        "rec": "0",
        "yds": "0",
        "td": "0",
        "lng": "0"
      },
      "fumbles": {
        "fmb": "0",
        "fl": "0"
      }
    }
  ]
}