{
  "boxScoreLink": "/boxscores/201510150nor.htm",
  "playerStatsList": [
    {
      "playerLink": "/players/R/RyanMa00.htm",
      "playerName": "Matt Ryan",
      "team": "ATL",
      "passing": {
        "cmp": "30",
        "att": "44",
        "yds": "295",
        "td": "2",
        "int": "0",
        "sk": "5",
        "lng": "30",
        "rate": "102.0"
      },
      "rushing": {
        "att": "4",
        "yds": "10",
        "td": "0",
        "lng": "5"
      },
      "receiving": {
        "tgt": "0",
        "rec": "0",
        "yds": "0",
        "td": "0",
        "lng": "0"
      },
      "fumbles": {
        "fmb": "3",
        "fl": "1"
      }
    },
    {
      "playerLink": "/players/F/FreeDe00.htm",
      "playerName": "Devonta Freeman",
      "team": "ATL",
      "passing": {
        "cmp": "0",
        "att": "0",
        "yds": "0",
        "td": "0",
        "int": "0",
        "sk": "0",
        "lng": "0",
        "rate": ""
      },
      "rushing": {
        "att": "13",
        "yds": "100",
        "td": "1",
        "lng": "25"
      },
      "receiving": {
        "tgt": "10",
        "rec": "8",
        "yds": "56",
        "td": "1",
        "lng": "13"
      },
      "fumbles": {
        "fmb": "0",
        "fl": "0"
      }
    },
    {
      "playerLink": "/players/C/ColeTe01.htm",
      "playerName": "Tevin Coleman",
      "team": "ATL",
      "passing": {
        "cmp": "0",
        "att": "0",
        "yds": "0",
        "td": "0",
        "int": "0",
        "sk": "0",
        "lng": "0",
        "rate": ""
      },
      "rushing": {
        "att": "4",
        "yds": "40",
        "td": "0",
        "lng": "18"
      },
      "receiving": {
        "tgt": "0",
        "rec": "0",
        "yds": "0",
        "td": "0",
        "lng": "0"
      },
      "fumbles": {
        "fmb": "1",
        "fl": "1"
      }
    },
    {
      "playerLink": "/players/J/JoneJu02.htm",
      "playerName": "Julio Jones",
      "team": "ATL",
      "passing": {
        "cmp": "0",
        "att": "0",
        "yds": "0",
        "td": "0",
        "int": "0",
        "sk": "0",
        "lng": "0",
        "rate": ""
      },
      "rushing": {
        "att": "0",
        "yds": "0",
        "td": "0",
        "lng": "0"
      },
      "receiving": {
        "tgt": "10",
        "rec": "6",
        "yds": "93",
        "td": "0",
        "lng": "30"
      },
      "fumbles": {
        "fmb": "0",
        "fl": "0"
      }
    },
    {
      "playerLink": "/players/H/HankLe00.htm",
      "playerName": "Leonard Hankerson",
      "team": "ATL",
      "passing": {
        "cmp": "0",
        "att": "0",
        "yds": "0",
        "td": "0",
        "int": "0",
        "sk": "0",
        "lng": "0",
        "rate": ""
      },
      "rushing": {
        "att": "0",
        "yds": "0",
        "td": "0",
        "lng": "0"
      },
      "receiving": {
        "tgt": "6",
        "rec": "4",
        "yds": "37",
        "td": "0",
        "lng": "12"
      },
      "fumbles": {
        "fmb": "0",
        "fl": "0"
      }
    },
    {
      "playerLink": "/players/T/TammJa00.htm",
      "playerName": "Jacob Tamme",
      "team": "ATL",
      "passing": {
        "cmp": "0",
        "att": "0",
        "yds": "0",
        "td": "0",
        "int": "0",
        "sk": "0",
        "lng": "0",
        "rate": ""
      },
      "rushing": {
        "att": "0",
        "yds": "0",
        "td": "0",
        "lng": "0"
      },
      "receiving": {
        "tgt": "5",
        "rec": "3",
        "yds": "32",
        "td": "0",
        "lng": "20"
      },
      "fumbles": {
        "fmb": "0",
        "fl": "0"
      }
    },
    {
      "playerLink": "/players/W/WhitRo00.htm",
      "playerName": "Roddy White",
      "team": "ATL",
      "passing": {
        "cmp": "0",
        "att": "0",
        "yds": "0",
        "td": "0",
        "int": "0",
        "sk": "0",
        "lng": "0",
        "rate": ""
      },
      "rushing": {
        "att": "0",
        "yds": "0",
        "td": "0",
        "lng": "0"
      },
      "receiving": {
        "tgt": "4",
        "rec": "3",
        "yds": "23",
        "td": "1",
        "lng": "8"
      },
      "fumbles": {
        "fmb": "0",
        "fl": "0"
      }
    },
    {
      "playerLink": "/players/T/ToilLe00.htm",
      "playerName": "Levine Toilolo",
      "team": "ATL",
      "passing": {
        "cmp": "0",
        "att": "0",
        "yds": "0",
        "td": "0",
        "int": "0",
        "sk": "0",
        "lng": "0",
        "rate": ""
      },
      "rushing": {
        "att": "0",
        "yds": "0",
        "td": "0",
        "lng": "0"
      },
      "receiving": {
        "tgt": "3",
        "rec": "2",
        "yds": "18",
        "td": "0",
        "lng": "11"
      },
      "fumbles": {
        "fmb": "0",
        "fl": "0"
      }
    },
    {
      "playerLink": "/players/D/DiMaPa00.htm",
      "playerName": "Patrick DiMarco",
      "team": "ATL",
      "passing": {
        "cmp": "0",
        "att": "0",
        "yds": "0",
        "td": "0",
        "int": "0",
        "sk": "0",
        "lng": "0",
        "rate": ""
      },
      "rushing": {
        "att": "0",
        "yds": "0",
        "td": "0",
        "lng": "0"
      },
      "receiving": {
        "tgt": "3",
        "rec": "2",
        "yds": "18",
        "td": "0",
        "lng": "12"
      },
      "fumbles": {
        "fmb": "0",
        "fl": "0"
      }
    },
    {
      "playerLink": "/players/W/WillNi02.htm",
      "playerName": "Nick Williams",
      "team": "ATL",
      "passing": {
        "cmp": "0",
        "att": "0",
        "yds": "0",
        "td": "0",
        "int": "0",
        "sk": "0",
        "lng": "0",
        "rate": ""
      },
      "rushing": {
        "att": "0",
        "yds": "0",
        "td": "0",
        "lng": "0"
      },
      "receiving": {
        "tgt": "1",
        "rec": "1",
        "yds": "11",
        "td": "0",
        "lng": "11"
      },
      "fumbles": {
        "fmb": "0",
        "fl": "0"
      }
    },
    {
      "playerLink": "/players/W/WardTe00.htm",
      "playerName": "Terron Ward",
      "team": "ATL",
      "passing": {
        "cmp": "0",
        "att": "0",
        "yds": "0",
        "td": "0",
        "int": "0",
        "sk": "0",
        "lng": "0",
        "rate": ""
      },
      "rushing": {
        "att": "0",
        "yds": "0",
        "td": "0",
        "lng": "0"
      },
      "receiving": {
        "tgt": "1",
        "rec": "1",
        "yds": "7",
        "td": "0",
        "lng": "7"
      },
      "fumbles": {
        "fmb": "0",
        "fl": "0"
      }
    },
    {
      "playerLink": "/players/B/BreeDr00.htm",
      "playerName": "Drew Brees",
      "team": "NOR",
      "passing": {
        "cmp": "30",
        "att": "39",
        "yds": "312",
        "td": "1",
        "int": "0",
        "sk": "1",
        "lng": "28",
        "rate": "108.1"
      },
      "rushing": {
        "att": "2",
        "yds": "2",
        "td": "0",
        "lng": "3"
      },
      "receiving": {
        "tgt": "0",
        "rec": "0",
        "yds": "0",
        "td": "0",
        "lng": "0"
      },
      "fumbles": {
        "fmb": "0",
        "fl": "0"
      }
    },
    {
      "playerLink": "/players/I/IngrMa01.htm",
      "playerName": "Mark Ingram",
      "team": "NOR",
      "passing": {
        "cmp": "0",
        "att": "0",
        "yds": "0",
        "td": "0",
        "int": "0",
        "sk": "0",
        "lng": "0",
        "rate": ""
      },
      "rushing": {
        "att": "20",
        "yds": "46",
        "td": "2",
        "lng": "11"
      },
      "receiving": {
        "tgt": "3",
        "rec": "3",
        "yds": "10",
        "td": "0",
        "lng": "7"
      },
      "fumbles": {
        "fmb": "0",
        "fl": "0"
      }
    },
    {
      "playerLink": "/players/R/RobiKh00.htm",
      "playerName": "Khiry Robinson",
      "team": "NOR",
      "passing": {
        "cmp": "0",
        "att": "0",
        "yds": "0",
        "td": "0",
        "int": "0",
        "sk": "0",
        "lng": "0",
        "rate": ""
      },
      "rushing": {
        "att": "7",
        "yds": "23",
        "td": "0",
        "lng": "10"
      },
      "receiving": {
        "tgt": "2",
        "rec": "2",
        "yds": "24",
        "td": "0",
        "lng": "18"
      },
      "fumbles": {
        "fmb": "0",
        "fl": "0"
      }
    },
    {
      "playerLink": "/players/S/SpilC.00.htm",
      "playerName": "C.J. Spiller",
      "team": "NOR",
      "passing": {
        "cmp": "0",
        "att": "0",
        "yds": "0",
        "td": "0",
        "int": "0",
        "sk": "0",
        "lng": "0",
        "rate": ""
      },
      "rushing": {
        "att": "3",
        "yds": "10",
        "td": "0",
        "lng": "7"
      },
      "receiving": {
        "tgt": "5",
        "rec": "4",
        "yds": "17",
        "td": "0",
        "lng": "8"
      },
      "fumbles": {
        "fmb": "0",
        "fl": "0"
      }
    },
    {
      "playerLink": "/players/W/WatsBe00.htm",
      "playerName": "Ben Watson",
      "team": "NOR",
      "passing": {
        "cmp": "0",
        "att": "0",
        "yds": "0",
        "td": "0",
        "int": "0",
        "sk": "0",
        "lng": "0",
        "rate": ""
      },
      "rushing": {
        "att": "0",
        "yds": "0",
        "td": "0",
        "lng": "0"
      },
      "receiving": {
        "tgt": "12",
        "rec": "10",
        "yds": "127",
        "td": "1",
        "lng": "28"
      },
      "fumbles": {
        "fmb": "0",
        "fl": "0"
      }
    },
    {
      "playerLink": "/players/S/SneaWi00.htm",
      "playerName": "Willie Snead",
      "team": "NOR",
      "passing": {
        "cmp": "0",
        "att": "0",
        "yds": "0",
        "td": "0",
        "int": "0",
        "sk": "0",
        "lng": "0",
        "rate": ""
      },
      "rushing": {
        "att": "0",
        "yds": "0",
        "td": "0",
        "lng": "0"
      },
      "receiving": {
        "tgt": "5",
        "rec": "4",
        "yds": "55",
        "td": "0",
        "lng": "24"
      },
      "fumbles": {
        "fmb": "0",
        "fl": "0"
      }
    },
    {
      "playerLink": "/players/C/CookBr00.htm",
      "playerName": "Brandin Cooks",
      "team": "NOR",
      "passing": {
        "cmp": "0",
        "att": "0",
        "yds": "0",
        "td": "0",
        "int": "0",
        "sk": "0",
        "lng": "0",
        "rate": ""
      },
      "rushing": {
        "att": "0",
        "yds": "0",
        "td": "0",
        "lng": "0"
      },
      "receiving": {
        "tgt": "5",
        "rec": "4",
        "yds": "41",
        "td": "0",
        "lng": "26"
      },
      "fumbles": {
        "fmb": "0",
        "fl": "0"
      }
    },
    {
      "playerLink": "/players/H/HillJo02.htm",
      "playerName": "Josh Hill",
      "team": "NOR",
      "passing": {
        "cmp": "0",
        "att": "0",
        "yds": "0",
        "td": "0",
        "int": "0",
        "sk": "0",
        "lng": "0",
        "rate": ""
      },
      "rushing": {
        "att": "0",
        "yds": "0",
        "td": "0",
        "lng": "0"
      },
      "receiving": {
        "tgt": "5",
        "rec": "3",
        "yds": "38",
        "td": "0",
        "lng": "19"
      },
      "fumbles": {
        "fmb": "0",
        "fl": "0"
      }
    }
  ]
}