{
  "boxScoreLink": "/boxscores/201512030det.htm",
  "playerStatsList": [
    {
      "playerLink": "/players/R/RodgAa00.htm",
      "playerName": "Aaron Rodgers",
      "team": "GNB",
      "passing": {
        "cmp": "24",
        "att": "36",
        "yds": "273",
        "td": "2",
        "int": "1",
        "sk": "3",
        "lng": "61",
        "rate": "96.2"
      },
      "rushing": {
        "att": "4",
        "yds": "27",
        "td": "1",
        "lng": "17"
      },
      "receiving": {
        "tgt": "0",
        "rec": "0",
        "yds": "0",
        "td": "0",
        "lng": "0"
      },
      "fumbles": {
        "fmb": "1",
        "fl": "0"
      }
    },
    {
      "playerLink": "/players/C/CrocJo00.htm",
      "playerName": "John Crockett",
      "team": "GNB",
      "passing": {
        "cmp": "0",
        "att": "0",
        "yds": "0",
        "td": "0",
        "int": "0",
        "sk": "0",
        "lng": "0",
        "rate": ""
      },
      "rushing": {
        "att": "5",
        "yds": "22",
        "td": "0",
        "lng": "12"
      },
      "receiving": {
        "tgt": "0",
        "rec": "0",
        "yds": "0",
        "td": "0",
        "lng": "0"
      },
      "fumbles": {
        "fmb": "0",
        "fl": "0"
      }
    },
    {
      "playerLink": "/players/S/StarJa00.htm",
      "playerName": "James Starks",
      "team": "GNB",
      "passing": {
        "cmp": "0",
        "att": "0",
        "yds": "0",
        "td": "0",
        "int": "0",
        "sk": "0",
        "lng": "0",
        "rate": ""
      },
      "rushing": {
        "att": "9",
        "yds": "15",
        "td": "0",
        "lng": "6"
      },
      "receiving": {
        "tgt": "7",
        "rec": "5",
        "yds": "45",
        "td": "0",
        "lng": "25"
      },
      "fumbles": {
        "fmb": "2",
        "fl": "0"
      }
    },
    {
      "playerLink": "/players/L/LacyEd00.htm",
      "playerName": "Eddie Lacy",
      "team": "GNB",
      "passing": {
        "cmp": "0",
        "att": "0",
        "yds": "0",
        "td": "0",
        "int": "0",
        "sk": "0",
        "lng": "0",
        "rate": ""
      },
      "rushing": {
        "att": "5",
        "yds": "4",
        "td": "0",
        "lng": "2"
      },
      "receiving": {
        "tgt": "1",
        "rec": "1",
        "yds": "-3",
        "td": "0",
        "lng": "-3"
      },
      "fumbles": {
        "fmb": "0",
        "fl": "0"
      }
    },
    {
      "playerLink": "/players/R/RodgRi00.htm",
      "playerName": "Richard Rodgers",
      "team": "GNB",
      "passing": {
        "cmp": "0",
        "att": "0",
        "yds": "0",
        "td": "0",
        "int": "0",
        "sk": "0",
        "lng": "0",
        "rate": ""
      },
      "rushing": {
        "att": "0",
        "yds": "0",
        "td": "0",
        "lng": "0"
      },
      "receiving": {
        "tgt": "8",
        "rec": "8",
        "yds": "146",
        "td": "1",
        "lng": "61"
      },
      "fumbles": {
        "fmb": "0",
        "fl": "0"
      }
    },
    {
      "playerLink": "/players/A/AdamDa01.htm",
      "playerName": "Davante Adams",
      "team": "GNB",
      "passing": {
        "cmp": "0",
        "att": "0",
        "yds": "0",
        "td": "0",
        "int": "0",
        "sk": "0",
        "lng": "0",
        "rate": ""
      },
      "rushing": {
        "att": "0",
        "yds": "0",
        "td": "0",
        "lng": "0"
      },
      "receiving": {
        "tgt": "7",
        "rec": "4",
        "yds": "21",
        "td": "1",
        "lng": "8"
      },
      "fumbles": {
        "fmb": "0",
        "fl": "0"
      }
    },
    {
      "playerLink": "/players/J/JoneJa04.htm",
      "playerName": "James Jones",
      "team": "GNB",
      "passing": {
        "cmp": "0",
        "att": "0",
        "yds": "0",
        "td": "0",
        "int": "0",
        "sk": "0",
        "lng": "0",
        "rate": ""
      },
      "rushing": {
        "att": "0",
        "yds": "0",
        "td": "0",
        "lng": "0"
      },
      "receiving": {
        "tgt": "3",
        "rec": "1",
        "yds": "19",
        "td": "0",
        "lng": "19"
      },
      "fumbles": {
        "fmb": "0",
        "fl": "0"
      }
    },
    {
      "playerLink": "/players/A/AbbrJa00.htm",
      "playerName": "Jared Abbrederis",
      "team": "GNB",
      "passing": {
        "cmp": "0",
        "att": "0",
        "yds": "0",
        "td": "0",
        "int": "0",
        "sk": "0",
        "lng": "0",
        "rate": ""
      },
      "rushing": {
        "att": "0",
        "yds": "0",
        "td": "0",
        "lng": "0"
      },
      "receiving": {
        "tgt": "3",
        "rec": "1",
        "yds": "16",
        "td": "0",
        "lng": "16"
      },
      "fumbles": {
        "fmb": "0",
        "fl": "0"
      }
    },
    {
      "playerLink": "/players/C/CobbRa00.htm",
      "playerName": "Randall Cobb",
      "team": "GNB",
      "passing": {
        "cmp": "0",
        "att": "0",
        "yds": "0",
        "td": "0",
        "int": "0",
        "sk": "0",
        "lng": "0",
        "rate": ""
      },
      "rushing": {
        "att": "1",
        "yds": "-1",
        "td": "0",
        "lng": "-1"
      },
      "receiving": {
        "tgt": "5",
        "rec": "4",
        "yds": "29",
        "td": "0",
        "lng": "16"
      },
      "fumbles": {
        "fmb": "0",
        "fl": "0"
      }
    },
    {
      "playerLink": "/players/S/StafMa00.htm",
      "playerName": "Matthew Stafford",
      "team": "DET",
      "passing": {
        "cmp": "23",
        "att": "35",
        "yds": "220",
        "td": "2",
        "int": "0",
        "sk": "3",
        "lng": "29",
        "rate": "102.1"
      },
      "rushing": {
        "att": "2",
        "yds": "22",
        "td": "0",
        "lng": "12"
      },
      "receiving": {
        "tgt": "0",
        "rec": "0",
        "yds": "0",
        "td": "0",
        "lng": "0"
      },
      "fumbles": {
        "fmb": "1",
        "fl": "1"
      }
    },
    {
      "playerLink": "/players/A/AbduAm00.htm",
      "playerName": "Ameer Abdullah",
      "team": "DET",
      "passing": {
        "cmp": "0",
        "att": "0",
        "yds": "0",
        "td": "0",
        "int": "0",
        "sk": "0",
        "lng": "0",
        "rate": ""
      },
      "rushing": {
        "att": "13",
        "yds": "67",
        "td": "0",
        "lng": "36"
      },
      "receiving": {
        "tgt": "1",
        "rec": "0",
        "yds": "0",
        "td": "0",
        "lng": "0"
      },
      "fumbles": {
        "fmb": "0",
        "fl": "0"
      }
    },
    {
      "playerLink": "/players/B/BellJo01.htm",
      "playerName": "Joique Bell",
      "team": "DET",
      "passing": {
        "cmp": "0",
        "att": "0",
        "yds": "0",
        "td": "0",
        "int": "0",
        "sk": "0",
        "lng": "0",
        "rate": ""
      },
      "rushing": {
        "att": "8",
        "yds": "5",
        "td": "0",
        "lng": "6"
      },
      "receiving": {
        "tgt": "2",
        "rec": "2",
        "yds": "25",
        "td": "0",
        "lng": "18"
      },
      "fumbles": {
        "fmb": "0",
        "fl": "0"
      }
    },
    {
      "playerLink": "/players/R/RiddTh00.htm",
      "playerName": "Theo Riddick",
      "team": "DET",
      "passing": {
        "cmp": "0",
        "att": "0",
        "yds": "0",
        "td": "0",
        "int": "0",
        "sk": "0",
        "lng": "0",
        "rate": ""
      },
      "rushing": {
        "att": "1",
        "yds": "4",
        "td": "0",
        "lng": "4"
      },
      "receiving": {
        "tgt": "6",
        "rec": "5",
        "yds": "27",
        "td": "0",
        "lng": "9"
      },
      "fumbles": {
        "fmb": "0",
        "fl": "0"
      }
    },
    {
      "playerLink": "/players/T/TateGo00.htm",
      "playerName": "Golden Tate",
      "team": "DET",
      "passing": {
        "cmp": "0",
        "att": "0",
        "yds": "0",
        "td": "0",
        "int": "0",
        "sk": "0",
        "lng": "0",
        "rate": ""
      },
      "rushing": {
        "att": "1",
        "yds": "3",
        "td": "0",
        "lng": "3"
      },
      "receiving": {
        "tgt": "10",
        "rec": "8",
        "yds": "63",
        "td": "0",
        "lng": "13"
      },
      "fumbles": {
        "fmb": "0",
        "fl": "0"
      }
    },
    {
      "playerLink": "/players/J/JohnCa00.htm",
      "playerName": "Calvin Johnson",
      "team": "DET",
      "passing": {
        "cmp": "0",
        "att": "0",
        "yds": "0",
        "td": "0",
        "int": "0",
        "sk": "0",
        "lng": "0",
        "rate": ""
      },
      "rushing": {
        "att": "0",
        "yds": "0",
        "td": "0",
        "lng": "0"
      },
      "receiving": {
        "tgt": "8",
        "rec": "3",
        "yds": "44",
        "td": "1",
        "lng": "20"
      },
      "fumbles": {
        "fmb": "0",
        "fl": "0"
      }
    },
    {
      "playerLink": "/players/J/JoneT.00.htm",
      "playerName": "T.J. Jones",
      "team": "DET",
      "passing": {
        "cmp": "0",
        "att": "0",
        "yds": "0",
        "td": "0",
        "int": "0",
        "sk": "0",
        "lng": "0",
        "rate": ""
      },
      "rushing": {
        "att": "0",
        "yds": "0",
        "td": "0",
        "lng": "0"
      },
      "receiving": {
        "tgt": "3",
        "rec": "2",
        "yds": "37",
        "td": "0",
        "lng": "29"
      },
      "fumbles": {
        "fmb": "0",
        "fl": "0"
      }
    },
    {
      "playerLink": "/players/F/FullCo00.htm",
      "playerName": "Corey Fuller",
      "team": "DET",
      "passing": {
        "cmp": "0",
        "att": "0",
        "yds": "0",
        "td": "0",
        "int": "0",
        "sk": "0",
        "lng": "0",
        "rate": ""
      },
      "rushing": {
        "att": "0",
        "yds": "0",
        "td": "0",
        "lng": "0"
      },
      "receiving": {
        "tgt": "2",
        "rec": "1",
        "yds": "15",
        "td": "0",
        "lng": "15"
      },
      "fumbles": {
        "fmb": "0",
        "fl": "0"
      }
    },
    {
      "playerLink": "/players/E/EbroEr00.htm",
      "playerName": "Eric Ebron",
      "team": "DET",
      "passing": {
        "cmp": "0",
        "att": "0",
        "yds": "0",
        "td": "0",
        "int": "0",
        "sk": "0",
        "lng": "0",
        "rate": ""
      },
      "rushing": {
        "att": "0",
        "yds": "0",
        "td": "0",
        "lng": "0"
      },
      "receiving": {
        "tgt": "2",
        "rec": "2",
        "yds": "9",
        "td": "1",
        "lng": "6"
      },
      "fumbles": {
        "fmb": "0",
        "fl": "0"
      }
    }
  ]
}